akbc/__init__.py
akbc/__main__.py
akbc/canbus_monitor.py
akbc/keyboard_controller.py
akbc/screen.py
akbc/simple_vehicle.py
akbc-0.0.6.dist-info/METADATA
akbc-0.0.6.dist-info/WHEEL
akbc-0.0.6.dist-info/entry_points.txt
akbc-0.0.6.dist-info/top_level.txt
akbc-0.0.6.dist-info/RECORD
