Metadata-Version: 2.4
Name: akbc
Version: 0.0.6
Summary: a simple keyboard controller for apollo
Author-email: Pride Leong <lykling.lyk@gmail.com>
Project-URL: Homepage, https://github.com/lykling/apollo-keyboard-controller/tree/main
Project-URL: Bug Tracker, https://github.com/lykling/apollo-keyboard-controller/issues
Requires-Python: >3.6
Requires-Dist: cantools
Requires-Dist: click
Requires-Dist: python-can
Requires-Dist: scipy
Requires-Dist: setuptools
Requires-Dist: numpy
